odoo8_addon_account_move_line_no_default_search-8.0.0.1.0-py2.7-nspkg.pth
odoo_addons/account_move_line_no_default_search/__openerp__.py
odoo_addons/account_move_line_no_default_search/__init__.py
odoo_addons/account_move_line_no_default_search/views/move_line_search_view.xml
odoo_addons/account_move_line_no_default_search/static/description/sample.png
odoo_addons/account_move_line_no_default_search/static/description/icon.png
odoo_addons/account_move_line_no_default_search/static/src/js/move_line_search_view.js
odoo8_addon_account_move_line_no_default_search-8.0.0.1.0.dist-info/top_level.txt
odoo8_addon_account_move_line_no_default_search-8.0.0.1.0.dist-info/WHEEL
odoo8_addon_account_move_line_no_default_search-8.0.0.1.0.dist-info/RECORD
odoo8_addon_account_move_line_no_default_search-8.0.0.1.0.dist-info/metadata.json
odoo8_addon_account_move_line_no_default_search-8.0.0.1.0.dist-info/DESCRIPTION.rst
odoo8_addon_account_move_line_no_default_search-8.0.0.1.0.dist-info/METADATA
odoo8_addon_account_move_line_no_default_search-8.0.0.1.0.dist-info/namespace_packages.txt
