Metadata-Version: 2.0
Name: odoo8-addon-account-move-line-no-default-search
Version: 8.0.0.1.0
Summary: Move line search view - disable defaults for period and journal
Home-page: http://therp.nl
Author: UNKNOWN
Author-email: UNKNOWN
License: AGPL-3
Platform: UNKNOWN
Requires-Dist: odoo (<9.0a,>=8.0a)
Classifier: Programming Language :: Python :: 2.7
Classifier: Framework :: Odoo
Classifier: License :: OSI Approved :: GNU Affero General Public License v3
